simple_hierarchical_transformer/__init__.py
simple_hierarchical_transformer/attention.py
simple_hierarchical_transformer/simple_hierarchical_transformer.py
simple_hierarchical_transformer-0.2.0.dist-info/LICENSE
simple_hierarchical_transformer-0.2.0.dist-info/METADATA
simple_hierarchical_transformer-0.2.0.dist-info/WHEEL
simple_hierarchical_transformer-0.2.0.dist-info/top_level.txt
simple_hierarchical_transformer-0.2.0.dist-info/RECORD
