Metadata-Version: 2.1
Name: simple-hierarchical-transformer
Version: 0.2.0
Summary: Simple Hierarchical Transformer
Home-page: https://github.com/lucidrains/simple-hierarchical-transformer
Author: Phil Wang
Author-email: lucidrains@gmail.com
License: MIT
Keywords: artificial intelligence,deep learning,transformers,attention mechanism,hierarchical
Classifier: Development Status :: 4 - Beta
Classifier: Intended Audience :: Developers
Classifier: Topic :: Scientific/Engineering :: Artificial Intelligence
Classifier: License :: OSI Approved :: MIT License
Classifier: Programming Language :: Python :: 3.6
License-File: LICENSE
Requires-Dist: accelerate
Requires-Dist: einops >=0.7.0
Requires-Dist: local-attention
Requires-Dist: torch >=2.0
